CHANGELOG.md
LICENSE
MANIFEST.in
README.md
REQUIREMENTS.txt
_version.py
setup.py
verify_setup.py
mcwpy/__init__.py
mcwpy/datapack.py
mcwpy/utility.py
mcwpy/workspace.py
mcwpy.egg-info/PKG-INFO
mcwpy.egg-info/SOURCES.txt
mcwpy.egg-info/dependency_links.txt
mcwpy.egg-info/not-zip-safe
mcwpy.egg-info/requires.txt
mcwpy.egg-info/top_level.txt
mcwpy/tests/datapack.py