Metadata-Version: 2.1
Name: mcwpy
Version: 0.0.12
Summary: A new way to create Minecraft datapacks
Home-page: https://github.com/vianneyveremme/minecraft_with_python
Author: Vianpyro
Author-email: vianney.veremme@gmail.com
License: MIT
Keywords: Minecraft,Datapack,Function,MCFunction
Platform: UNKNOWN
Classifier: Development Status :: 1 - Planning
Classifier: Intended Audience :: Customer Service
Classifier: Intended Audience :: Developers
Classifier: Intended Audience :: Education
Classifier: Intended Audience :: End Users/Desktop
Classifier: Operating System :: OS Independent
Classifier: License :: OSI Approved :: MIT License
Classifier: Programming Language :: Python :: 3
Classifier: Programming Language :: Python :: 3.9
